norma43utils/__init__.py
norma43utils/services/__init__.py
norma43utils/services/google_spreadsheet_service.py
norma43utils/services/service.py
norma43utils-1.0.4.data/scripts/norma43utils-bin
norma43utils-1.0.4.dist-info/LICENSE.txt
norma43utils-1.0.4.dist-info/METADATA
norma43utils-1.0.4.dist-info/WHEEL
norma43utils-1.0.4.dist-info/top_level.txt
norma43utils-1.0.4.dist-info/RECORD
