Metadata-Version: 2.1
Name: norma43utils
Version: 1.0.4
Summary: Utils for norma43 files, like exporting to Google Spreadsheets or CSV
Home-page: https://github.com/sergief/norma43utils
Author: Sergi Espinar
Author-email: sergief@users.noreply.github.com
License: MIT
Keywords: norma43,utils,bank,account,n43,csb,google,spreadsheets,csv
Platform: UNKNOWN
Classifier: Development Status :: 4 - Beta
Classifier: Intended Audience :: End Users/Desktop
Classifier: Topic :: Office/Business :: Financial
Classifier: License :: OSI Approved :: MIT License
Classifier: Programming Language :: Python :: 3.6
Classifier: Programming Language :: Python :: 3.7
Classifier: Programming Language :: Python :: 3.8
Requires-Python: >=3.6
Requires-Dist: norma43parser (<2.0.0,>=1.1.2)
Requires-Dist: google-api-python-client (<1.9.0,>=1.8.0)
Requires-Dist: google-auth-httplib2 (<0.1.0,>=0.0.3)
Requires-Dist: google-auth-oauthlib (<0.5.0,>=0.4.1)
